[
  "Template",
  {
    "verbose": true,
    "solution_template": {
      "update_strategy": [
        "Default"
      ],
      "default_template": [
        "DefaultQualifier"
      ],
      "update_threshold": null,
      "default_seeds": false,
      "predicate_template": [
        "Filename",
        "./config/pcsat/template/dbg_predicate_template.json"
      ],
      "wf_predicate_template": [
        "Filename",
        "./config/pcsat/template/dbg_wf_predicate_template.json"
      ],
      "fn_predicate_template": [
        "Filename",
        "./config/pcsat/template/dbg_fn_predicate_template.json"
      ]
    }
  }
]